logicycl/__init__.py
logicycl/core.py
logicycl/entity.py
logicycl-0.0.2b0.dist-info/LICENSE
logicycl-0.0.2b0.dist-info/METADATA
logicycl-0.0.2b0.dist-info/WHEEL
logicycl-0.0.2b0.dist-info/top_level.txt
logicycl-0.0.2b0.dist-info/RECORD
