Metadata-Version: 2.1
Name: logicycl
Version: 0.0.2b0
Summary: Lib for generating logical express
Home-page: https://github.com/StephenKevin/logicycl
Author: StephenKevin
Author-email: hyuncankun@outlook.com
License: UNKNOWN
Platform: UNKNOWN
Classifier: Programming Language :: Python :: 3
Classifier: License :: OSI Approved :: MIT License
Classifier: Operating System :: OS Independent
Requires-Python: >=3.7
